bactopia/__init__.py
bactopia/atb.py
bactopia/cli/__init__.py
bactopia/cli/atb/__init__.py
bactopia/cli/atb/atb_downloader.py
bactopia/cli/atb/atb_formatter.py
bactopia/cli/citations.py
bactopia/cli/datasets.py
bactopia/cli/download.py
bactopia/cli/helpers/__init__.py
bactopia/cli/helpers/merge_schemas.py
bactopia/cli/jsonify.py
bactopia/cli/prepare.py
bactopia/cli/pubmlst/build.py
bactopia/cli/pubmlst/setup.py
bactopia/cli/search.py
bactopia/cli/summary.py
bactopia/cli/update.py
bactopia/cli/workflows.py
bactopia/databases/__init__.py
bactopia/databases/ena.py
bactopia/databases/ncbi.py
bactopia/databases/pubmlst/__init__.py
bactopia/databases/pubmlst/constants.py
bactopia/databases/pubmlst/utils.py
bactopia/parse.py
bactopia/parsers/__init__.py
bactopia/parsers/amrfinderplus.py
bactopia/parsers/annotator.py
bactopia/parsers/ariba.py
bactopia/parsers/assembler.py
bactopia/parsers/blast.py
bactopia/parsers/error.py
bactopia/parsers/gather.py
bactopia/parsers/generic.py
bactopia/parsers/mapping.py
bactopia/parsers/mlst.py
bactopia/parsers/parsables.py
bactopia/parsers/qc.py
bactopia/parsers/sketcher.py
bactopia/parsers/variants.py
bactopia/parsers/versions.py
bactopia/parsers/workflows.py
bactopia/reports/__init__.py
bactopia/reports/templates/__init__.py
bactopia/summary.py
bactopia/templates/nextflow-config.j2
bactopia/templates/nextflow_config.j2
bactopia/templates/nextflow_schema.json.j2
bactopia/utils.py
bactopia-1.7.0.dist-info/METADATA
bactopia-1.7.0.dist-info/WHEEL
bactopia-1.7.0.dist-info/entry_points.txt
bactopia-1.7.0.dist-info/licenses/LICENSE
bactopia-1.7.0.dist-info/RECORD
