Metadata-Version: 2.4
Name: bactopia
Version: 1.7.0
Summary: A Python package for working with Bactopia
License: MIT
License-File: LICENSE
Keywords: bioinformatics,bacteria,bactopia,SRA,ENA
Author: Robert A. Petit III
Author-email: robbie.petit@gmail.com
Requires-Python: >=3.9.0,<4.0.0
Classifier: License :: OSI Approved :: MIT License
Classifier: Programming Language :: Python :: 3
Classifier: Programming Language :: Python :: 3.9
Classifier: Programming Language :: Python :: 3.10
Classifier: Programming Language :: Python :: 3.11
Classifier: Programming Language :: Python :: 3.12
Classifier: Programming Language :: Python :: 3.13
Classifier: Programming Language :: Python :: 3.14
Requires-Dist: jinja2 (>=3.1.6,<4.0.0)
Requires-Dist: pandas (>=2.2.0,<3.0.0)
Requires-Dist: rauth (>=0.7.3,<0.8.0)
Requires-Dist: requests (>=2.28.2,<3.0.0)
Requires-Dist: rich (>=13.3.1,<14.0.0)
Requires-Dist: rich-click (>=1.6.1,<2.0.0)
Requires-Dist: tqdm (>=4.66.5,<5.0.0)
Project-URL: Homepage, https://bactopia.github.io/
Project-URL: Repository, https://github.com/bactopia/bactopia-py
